tacotron2_master/Gmodule.py
tacotron2_master/__init__.py
tacotron2_master/__main__.py
tacotron2_master/audio_processing.py
tacotron2_master/audio_utils.py
tacotron2_master/batch_resample_audio.py
tacotron2_master/cleaners.py
tacotron2_master/cmudict.py
tacotron2_master/cmudict_helper.py
tacotron2_master/constants.py
tacotron2_master/convert_model.py
tacotron2_master/convert_mp3_to_wav.py
tacotron2_master/data_utils.py
tacotron2_master/denoiser.py
tacotron2_master/distributed.py
tacotron2_master/generate_filelist.py
tacotron2_master/generate_train_val_files.py
tacotron2_master/giony_stft.py
tacotron2_master/glow.py
tacotron2_master/glow_old.py
tacotron2_master/helper.py
tacotron2_master/hparams.py
tacotron2_master/inference.py
tacotron2_master/layers.py
tacotron2_master/logger.py
tacotron2_master/loss_function.py
tacotron2_master/loss_scaler.py
tacotron2_master/main.py
tacotron2_master/mel2samp.py
tacotron2_master/model.py
tacotron2_master/multiproc.py
tacotron2_master/normalizer.py
tacotron2_master/number_utils.py
tacotron2_master/numbers1.py
tacotron2_master/path_test.py
tacotron2_master/platform_helper.py
tacotron2_master/plotting_utils.py
tacotron2_master/replace_stft.py
tacotron2_master/resample_audio.py
tacotron2_master/resource_loader.py
tacotron2_master/setup.py
tacotron2_master/speak.py
tacotron2_master/stft.py
tacotron2_master/stft_module.py
tacotron2_master/stft_utils.py
tacotron2_master/symbols.py
tacotron2_master/tacotron2_core.py
tacotron2_master/tacotron2_model.py
tacotron2_master/tacotron2_module.py
tacotron2_master/tacotron2_runner.py
tacotron2_master/test_imports.py
tacotron2_master/test_text_processing.py
tacotron2_master/text_processing.py
tacotron2_master/train.py
tacotron2_master/utils.py
tacotron2_master/utils_audio.py
tacotron2_master/utils_custom.py
tacotron2_master/utils_imports.py
tacotron2_master/verify_path.py
AI_Defender-1.0.0.dist-info/METADATA
AI_Defender-1.0.0.dist-info/WHEEL
AI_Defender-1.0.0.dist-info/entry_points.txt
AI_Defender-1.0.0.dist-info/top_level.txt
AI_Defender-1.0.0.dist-info/RECORD
