Metadata-Version: 2.1
Name: AI_Defender
Version: 1.0.0
Summary: A sample Python project for AI Defender
Home-page: https://github.com/GionyOrtiz/ai_defender
Author: Giony Ortiz
Author-email: gionyortiz@gmail.com
Project-URL: Bug Reports, https://github.com/GionyOrtiz/ai_defender/issues
Project-URL: Source, https://github.com/GionyOrtiz/ai_defender/
Keywords: sample setuptools development
Classifier: Development Status :: 3 - Alpha
Classifier: Intended Audience :: Developers
Classifier: Topic :: Software Development :: Build Tools
Classifier: License :: OSI Approved :: MIT License
Classifier: Programming Language :: Python :: 3
Classifier: Programming Language :: Python :: 3.7
Classifier: Programming Language :: Python :: 3.8
Classifier: Programming Language :: Python :: 3.9
Provides-Extra: dev
Requires-Dist: check-manifest; extra == "dev"
Provides-Extra: test
Requires-Dist: coverage; extra == "test"
